crystallography/__init__.py
crystallography-0.0.0.dist-info/LICENSE
crystallography-0.0.0.dist-info/WHEEL
crystallography-0.0.0.dist-info/METADATA
crystallography-0.0.0.dist-info/RECORD
